{
  "record_kind": "deep_link_navigation_truth_stable_case",
  "schema_version": 1,
  "case_name": "destination_visibility_drift_blocks_stable",
  "scenario": "A cross-root recoverable placeholder row has a remap packet and continuity record whose destination-visibility rows disagree on target_root_label; the validator fires destination_visibility_drift and the packet narrows below stable.",
  "input": {
    "packet_id": "packet:fixture:deep_link_nav:dest_drift",
    "workflow_or_surface_id": "workflow.search.deep_link_navigation.dest_drift",
    "query_session_id_ref": "search:session:fixture:dest_drift",
    "generated_at": "2026-05-26T12:00:00Z",
    "covered_outcomes": ["recoverable_placeholder"],
    "covered_drift_states": ["target_scope_excluded"],
    "rows": [
      {
        "row_id": "row:dest_drift:cross_root",
        "artifact_class": "navigation_history_entry",
        "origin_class": "back_forward",
        "remap_packet": {
          "record_kind": "deep_link_remap_packet_record",
          "deep_link_remap_packet_schema_version": 1,
          "remap_packet_id": "search:remap_packet:dest_drift:01",
          "deep_link_id_ref": "search:deep_link:dest_drift:01",
          "deep_link_drift_state": "target_scope_excluded",
          "outcome_class": "recoverable_placeholder",
          "old_target": {
            "target_kind": "workspace_file",
            "target_ref": "workspace:file:dest_drift:old",
            "workspace_id_ref": "workspace:monorepo",
            "root_id_ref": "root:app",
            "root_label": "app"
          },
          "new_target": {
            "target_kind": "workspace_file",
            "target_ref": "workspace:file:dest_drift:new",
            "workspace_id_ref": "workspace:monorepo",
            "root_id_ref": "root:shared",
            "root_label": "shared"
          },
          "scope": {
            "originating_workspace_id_ref": "workspace:monorepo",
            "active_workspace_id_ref": "workspace:monorepo",
            "stable_scope_id_ref": "scope:monorepo:app_only",
            "scope_class": "selected_workset",
            "scope_mode": "sparse",
            "workset_id_ref": "workset:app_only",
            "workset_name": "App only",
            "active_root_refs": ["root:app"],
            "destination_workspace_id_ref": "workspace:monorepo",
            "destination_root_id_ref": "root:shared",
            "destination_root_label": "shared",
            "destination_in_active_scope": false
          },
          "confidence": {
            "confidence_class": "structural",
            "confidence_score": 80,
            "evidence_classes": ["symbol_stable_id"]
          },
          "remap_chain_refs": [],
          "destination_visibility": [
            {
              "surface_class": "peek",
              "target_root_id_ref": "root:shared",
              "target_root_label": "shared",
              "destination_repo_visible": true
            },
            {
              "surface_class": "preview",
              "target_root_id_ref": "root:shared",
              "target_root_label": "shared",
              "destination_repo_visible": true
            },
            {
              "surface_class": "split",
              "target_root_id_ref": "root:shared",
              "target_root_label": "shared",
              "destination_repo_visible": true
            },
            {
              "surface_class": "open_in_new_pane",
              "target_root_id_ref": "root:shared",
              "target_root_label": "shared",
              "destination_repo_visible": true
            },
            {
              "surface_class": "back_navigation",
              "target_root_id_ref": "root:shared",
              "target_root_label": "shared",
              "destination_repo_visible": true
            }
          ],
          "recovery_actions": [
            "widen_scope",
            "open_target_root",
            "keep_current_scope",
            "inspect_remap_packet"
          ],
          "failure_reason": "target_scope_excluded",
          "emitted_at": "2026-05-26T12:00:00Z"
        },
        "continuity_record": {
          "record_kind": "navigation_continuity_record",
          "navigation_continuity_schema_version": 1,
          "continuity_id": "navigation:continuity:dest_drift:01",
          "artifact_kind": "navigation_history_entry",
          "artifact_id_ref": "history:back_forward:dest_drift",
          "deep_link_id_ref": "search:deep_link:dest_drift:01",
          "remap_packet_id_ref": "search:remap_packet:dest_drift:01",
          "continuity_state": "recoverable_placeholder",
          "origin_class": "back_forward",
          "scope_identity": {
            "workspace_id_ref": "workspace:monorepo",
            "stable_scope_id_ref": "scope:monorepo:app_only",
            "scope_class": "selected_workset",
            "scope_mode": "sparse",
            "workset_id_ref": "workset:app_only",
            "workset_name": "App only",
            "active_root_refs": ["root:app"],
            "target_workspace_id_ref": "workspace:monorepo",
            "target_root_id_ref": "root:shared",
            "target_root_label": "shared"
          },
          "destination_visibility": [
            {
              "surface_class": "peek",
              "target_root_id_ref": "root:shared",
              "target_root_label": "shared (renamed)",
              "destination_repo_visible": true
            },
            {
              "surface_class": "preview",
              "target_root_id_ref": "root:shared",
              "target_root_label": "shared",
              "destination_repo_visible": true
            },
            {
              "surface_class": "split",
              "target_root_id_ref": "root:shared",
              "target_root_label": "shared",
              "destination_repo_visible": true
            },
            {
              "surface_class": "open_in_new_pane",
              "target_root_id_ref": "root:shared",
              "target_root_label": "shared",
              "destination_repo_visible": true
            },
            {
              "surface_class": "back_navigation",
              "target_root_id_ref": "root:shared",
              "target_root_label": "shared",
              "destination_repo_visible": true
            }
          ],
          "recovery_actions": [
            "widen_scope",
            "open_target_root",
            "keep_current_scope",
            "inspect_remap_packet"
          ],
          "failure_reason": "target_scope_excluded",
          "placeholder_ref": "placeholder:dest_drift:shared_util",
          "emitted_at": "2026-05-26T12:00:00Z"
        },
        "display_title": "shared/util.rs (outside active workset)",
        "raw_boundary_material_excluded": true,
        "captured_at": "2026-05-26T12:00:00Z"
      }
    ],
    "consumer_projections": [
      {
        "consumer_surface": "search_shell",
        "projection_ref": "projection:search_shell:dest_drift",
        "export_packet_id_ref": "packet:fixture:deep_link_nav:dest_drift",
        "rendered_at": "2026-05-26T12:00:05Z",
        "preserves_same_packet": true,
        "preserves_remap_truth": true,
        "preserves_continuity_truth": true,
        "preserves_destination_visibility": true,
        "preserves_drift_state_vocabulary": true,
        "preserves_recovery_action_vocabulary": true,
        "preserves_confidence_and_evidence": true,
        "supports_json_export": true,
        "raw_private_material_excluded": true,
        "ambient_authority_excluded": true
      },
      {
        "consumer_surface": "navigation_history",
        "projection_ref": "projection:navigation_history:dest_drift",
        "export_packet_id_ref": "packet:fixture:deep_link_nav:dest_drift",
        "rendered_at": "2026-05-26T12:00:05Z",
        "preserves_same_packet": true,
        "preserves_remap_truth": true,
        "preserves_continuity_truth": true,
        "preserves_destination_visibility": true,
        "preserves_drift_state_vocabulary": true,
        "preserves_recovery_action_vocabulary": true,
        "preserves_confidence_and_evidence": true,
        "supports_json_export": true,
        "raw_private_material_excluded": true,
        "ambient_authority_excluded": true
      },
      {
        "consumer_surface": "docs_help",
        "projection_ref": "projection:docs_help:dest_drift",
        "export_packet_id_ref": "packet:fixture:deep_link_nav:dest_drift",
        "rendered_at": "2026-05-26T12:00:05Z",
        "preserves_same_packet": true,
        "preserves_remap_truth": true,
        "preserves_continuity_truth": true,
        "preserves_destination_visibility": true,
        "preserves_drift_state_vocabulary": true,
        "preserves_recovery_action_vocabulary": true,
        "preserves_confidence_and_evidence": true,
        "supports_json_export": true,
        "raw_private_material_excluded": true,
        "ambient_authority_excluded": true
      },
      {
        "consumer_surface": "ai_context_inspector",
        "projection_ref": "projection:ai_context_inspector:dest_drift",
        "export_packet_id_ref": "packet:fixture:deep_link_nav:dest_drift",
        "rendered_at": "2026-05-26T12:00:05Z",
        "preserves_same_packet": true,
        "preserves_remap_truth": true,
        "preserves_continuity_truth": true,
        "preserves_destination_visibility": true,
        "preserves_drift_state_vocabulary": true,
        "preserves_recovery_action_vocabulary": true,
        "preserves_confidence_and_evidence": true,
        "supports_json_export": true,
        "raw_private_material_excluded": true,
        "ambient_authority_excluded": true
      },
      {
        "consumer_surface": "cli_headless",
        "projection_ref": "projection:cli_headless:dest_drift",
        "export_packet_id_ref": "packet:fixture:deep_link_nav:dest_drift",
        "rendered_at": "2026-05-26T12:00:05Z",
        "preserves_same_packet": true,
        "preserves_remap_truth": true,
        "preserves_continuity_truth": true,
        "preserves_destination_visibility": true,
        "preserves_drift_state_vocabulary": true,
        "preserves_recovery_action_vocabulary": true,
        "preserves_confidence_and_evidence": true,
        "supports_json_export": true,
        "raw_private_material_excluded": true,
        "ambient_authority_excluded": true
      },
      {
        "consumer_surface": "support_export",
        "projection_ref": "projection:support_export:dest_drift",
        "export_packet_id_ref": "packet:fixture:deep_link_nav:dest_drift",
        "rendered_at": "2026-05-26T12:00:05Z",
        "preserves_same_packet": true,
        "preserves_remap_truth": true,
        "preserves_continuity_truth": true,
        "preserves_destination_visibility": true,
        "preserves_drift_state_vocabulary": true,
        "preserves_recovery_action_vocabulary": true,
        "preserves_confidence_and_evidence": true,
        "supports_json_export": true,
        "raw_private_material_excluded": true,
        "ambient_authority_excluded": true
      },
      {
        "consumer_surface": "release_proof_index",
        "projection_ref": "projection:release_proof_index:dest_drift",
        "export_packet_id_ref": "packet:fixture:deep_link_nav:dest_drift",
        "rendered_at": "2026-05-26T12:00:05Z",
        "preserves_same_packet": true,
        "preserves_remap_truth": true,
        "preserves_continuity_truth": true,
        "preserves_destination_visibility": true,
        "preserves_drift_state_vocabulary": true,
        "preserves_recovery_action_vocabulary": true,
        "preserves_confidence_and_evidence": true,
        "supports_json_export": true,
        "raw_private_material_excluded": true,
        "ambient_authority_excluded": true
      }
    ],
    "source_contract_refs": []
  },
  "expect": {
    "promotion_state": "blocks_stable",
    "validation_finding_count": 1,
    "row_count": 1,
    "outcome_tokens": ["recoverable_placeholder"],
    "drift_state_tokens": ["target_scope_excluded"],
    "support_export_safe": false,
    "expected_finding_kinds": ["destination_visibility_drift"]
  }
}
