{
  "record_kind": "stable_wasm_host_governance_case",
  "schema_version": 1,
  "case_name": "crash_loop_window_breach_narrows_to_preview",
  "packet_input": {
    "packet_id": "extensions.stable_wasm_host_governance.fixture.crash_loop_window_breach_narrows_to_preview",
    "generated_at": "2026-05-31T10:10:00Z",
    "identity": {
      "runtime_contract_ref": "runtime_v1_beta:initech.debugger@3.0.1",
      "extension_identity_ref": "ext:initech.debugger",
      "extension_version": "3.0.1",
      "source_package_ref": "pkg:initech.debugger@3.0.1",
      "governance_contract_version": 1,
      "publisher_trust_tier_class": "verified_publisher",
      "lifecycle_state_class": "active"
    },
    "runtime_class_declaration": {
      "runtime_class": "wasm_capability_sandbox",
      "execution_locus_class": "dedicated_subprocess"
    },
    "quota_axes": [
      {
        "axis_class": "linear_memory",
        "declared_limit_ref": "quota:initech.debugger.linear_memory.declared",
        "observed_peak_ref": "quota:initech.debugger.linear_memory.observed",
        "enforcement_state_class": "enforced_as_published",
        "pressure_class": "nominal",
        "bounded": true
      },
      {
        "axis_class": "execution_fuel",
        "declared_limit_ref": "quota:initech.debugger.execution_fuel.declared",
        "observed_peak_ref": "quota:initech.debugger.execution_fuel.observed",
        "enforcement_state_class": "enforced_as_published",
        "pressure_class": "nominal",
        "bounded": true
      },
      {
        "axis_class": "table_elements",
        "declared_limit_ref": "quota:initech.debugger.table_elements.declared",
        "observed_peak_ref": "quota:initech.debugger.table_elements.observed",
        "enforcement_state_class": "enforced_as_published",
        "pressure_class": "nominal",
        "bounded": true
      },
      {
        "axis_class": "instance_count",
        "declared_limit_ref": "quota:initech.debugger.instance_count.declared",
        "observed_peak_ref": "quota:initech.debugger.instance_count.observed",
        "enforcement_state_class": "enforced_as_published",
        "pressure_class": "nominal",
        "bounded": true
      },
      {
        "axis_class": "epoch_deadline",
        "declared_limit_ref": "quota:initech.debugger.epoch_deadline.declared",
        "observed_peak_ref": "quota:initech.debugger.epoch_deadline.observed",
        "enforcement_state_class": "enforced_as_published",
        "pressure_class": "nominal",
        "bounded": true
      },
      {
        "axis_class": "host_call_egress",
        "declared_limit_ref": "quota:initech.debugger.host_call_egress.declared",
        "observed_peak_ref": "quota:initech.debugger.host_call_egress.observed",
        "enforcement_state_class": "enforced_as_published",
        "pressure_class": "nominal",
        "bounded": true
      }
    ],
    "crash_loop": {
      "window_ref": "crash_loop_window:initech.debugger",
      "distinct_failures": 2,
      "disable_threshold": 3,
      "quarantine_threshold": 5,
      "state_class": "window_open"
    },
    "restart_budget": {
      "restart_posture_class": "exponential_backoff_bounded",
      "attempts_used": 2,
      "attempts_remaining": 1
    },
    "quarantine_posture": {
      "recovery_precondition_class": "next_session_cold_start",
      "trigger_rule_ref": "quarantine_rule:crash_loop_window_open",
      "visibility_surface_class": "install_review_inspector_and_pill"
    },
    "contributions": [
      {
        "contribution_id": "contrib:initech.debugger.attach_command",
        "contribution_kind_class": "command",
        "source_package_ref": "pkg:initech.debugger@3.0.1",
        "runtime_class": "wasm_capability_sandbox",
        "execution_locus_class": "dedicated_subprocess",
        "trust_tier_class": "verified_publisher",
        "used_permission_refs": ["cap:debug.attach"],
        "last_known_good_host_ref": "host:wasm_subprocess_isolated_v1",
        "host_state_class": "running_nominal",
        "summary_label": "Attach command warming after repeated subprocess restarts."
      },
      {
        "contribution_id": "contrib:initech.debugger.session_panel",
        "contribution_kind_class": "panel",
        "source_package_ref": "pkg:initech.debugger@3.0.1",
        "runtime_class": "wasm_capability_sandbox",
        "execution_locus_class": "dedicated_subprocess",
        "trust_tier_class": "verified_publisher",
        "used_permission_refs": [],
        "last_known_good_host_ref": "host:wasm_subprocess_isolated_v1",
        "host_state_class": "running_nominal",
        "summary_label": "Session panel held while the crash-loop window is open."
      }
    ],
    "claim": {
      "claimed_tier": "stable",
      "claim_basis_class": "enforcement_backed",
      "summary_label": "Initech debugger claims Stable but an open crash-loop window disables it for the session."
    },
    "consumer_surfaces": ["install_review", "runtime_inspector", "quarantine_flow", "diagnostics", "support_export"],
    "summary_label": "Initech debugger narrows to Preview while the crash-loop window is open."
  },
  "expected": {
    "claimed_tier": "stable",
    "effective_tier": "preview",
    "support_claim_class": "preview_governance_experimental_claim",
    "stable_claim": false,
    "downgraded": true,
    "downgrade_reasons": ["crash_loop_window_breached"],
    "quarantine_state_class": "disabled_until_next_session",
    "downgraded_host_banner_required": true,
    "blocks_activation": true,
    "attribution_complete": true,
    "all_quotas_enforced_as_published": true,
    "quota_axis_count": 6,
    "breached_quota_axis_count": 0,
    "active_contribution_count": 2,
    "quarantined_contribution_count": 0
  }
}
